nonebot_plugin_navicat/__init__.py
nonebot_plugin_navicat/command.py
nonebot_plugin_navicat/elasticsearch.py
nonebot_plugin_navicat/mongodb.py
nonebot_plugin_navicat/mysql.py
nonebot_plugin_navicat/postgre.py
nonebot_plugin_navicat/redis.py
nonebot_plugin_navicat/sqlite.py
nonebot_plugin_navicat-0.4.0.dist-info/LICENSE
nonebot_plugin_navicat-0.4.0.dist-info/METADATA
nonebot_plugin_navicat-0.4.0.dist-info/WHEEL
nonebot_plugin_navicat-0.4.0.dist-info/top_level.txt
nonebot_plugin_navicat-0.4.0.dist-info/RECORD
