Metadata-Version: 2.1
Name: nonebot-plugin-navicat
Version: 0.4.0
Summary: A batabase manager plugin for nonebot2,provide capability of connection to all kinds of databases
Home-page: https://github.com/synodriver/nonebot_plugin_navicat
Author: synodriver
Author-email: diguohuangjiajinweijun@gmail.com
License: GPLv3
Project-URL: Bug Tracker, https://github.com/synodriver/nonebot_plugin_navicat/issues
Keywords: nonebot
Classifier: Framework :: AsyncIO
Classifier: Operating System :: OS Independent
Classifier: License :: OSI Approved :: GNU General Public License v3 (GPLv3)
Classifier: Programming Language :: Python
Classifier: Programming Language :: Python :: 3.8
Classifier: Programming Language :: Python :: 3.9
Classifier: Programming Language :: Python :: 3.10
Classifier: Programming Language :: Python :: 3.11
Classifier: Programming Language :: Python :: 3.12
Classifier: Programming Language :: Python :: Implementation :: CPython
Requires-Python: >=3.7
License-File: LICENSE
Requires-Dist: nonebot2
Requires-Dist: databases >=0.9.0
Provides-Extra: all
Requires-Dist: redis >=5.0 ; extra == 'all'
Requires-Dist: motor ; extra == 'all'
Requires-Dist: aiomysql ; extra == 'all'
Requires-Dist: asyncpg ; extra == 'all'
Requires-Dist: aiosqlite ; extra == 'all'
Requires-Dist: elasticsearch ; extra == 'all'
Requires-Dist: aiohttp ; extra == 'all'
Provides-Extra: elasticsearch
Requires-Dist: elasticsearch ; extra == 'elasticsearch'
Requires-Dist: aiohttp ; extra == 'elasticsearch'
Provides-Extra: mongodb
Requires-Dist: motor ; extra == 'mongodb'
Provides-Extra: mysql
Requires-Dist: aiomysql ; extra == 'mysql'
Provides-Extra: postgresql
Requires-Dist: asyncpg ; extra == 'postgresql'
Provides-Extra: redis
Requires-Dist: redis >=5.0 ; extra == 'redis'
Provides-Extra: sqlite
Requires-Dist: aiosqlite ; extra == 'sqlite'
